odoo/addons/sale_margin_sync/README.rst
odoo/addons/sale_margin_sync/__init__.py
odoo/addons/sale_margin_sync/__manifest__.py
odoo/addons/sale_margin_sync/i18n/es.po
odoo/addons/sale_margin_sync/i18n/it.po
odoo/addons/sale_margin_sync/i18n/sale_margin_sync.pot
odoo/addons/sale_margin_sync/i18n/tr.po
odoo/addons/sale_margin_sync/models/__init__.py
odoo/addons/sale_margin_sync/models/stock_valuation_layer.py
odoo/addons/sale_margin_sync/readme/CONTRIBUTORS.md
odoo/addons/sale_margin_sync/readme/DESCRIPTION.md
odoo/addons/sale_margin_sync/static/description/icon.png
odoo/addons/sale_margin_sync/static/description/index.html
odoo/addons/sale_margin_sync/tests/__init__.py
odoo/addons/sale_margin_sync/tests/test_sale_margin_sync.py
odoo_addon_sale_margin_sync-18.0.1.0.0.3.dist-info/METADATA
odoo_addon_sale_margin_sync-18.0.1.0.0.3.dist-info/WHEEL
odoo_addon_sale_margin_sync-18.0.1.0.0.3.dist-info/top_level.txt
odoo_addon_sale_margin_sync-18.0.1.0.0.3.dist-info/RECORD
